connectionprovider/__init__.py
connectionprovider/gcp/__init__.py
connectionprovider/gcp/service_accounts/__init__.py
connectionprovider/gcp/service_accounts/management.py
connectionprovider-0.1.1.dist-info/METADATA
connectionprovider-0.1.1.dist-info/WHEEL
connectionprovider-0.1.1.dist-info/top_level.txt
connectionprovider-0.1.1.dist-info/RECORD
