Metadata-Version: 2.1
Name: connectionprovider
Version: 0.1.1
Summary: A sample installable Python module.
Home-page: https://example.com/your_project_url
Author: Your Name
Author-email: your.email@example.com
License: UNKNOWN
Project-URL: Bug Reports, https://example.com/your_project_url/issues
Project-URL: Source, https://example.com/your_project_url
Platform: UNKNOWN
Classifier: Development Status :: 3 - Alpha
Classifier: Intended Audience :: Developers
Classifier: License :: OSI Approved :: MIT License
Classifier: Programming Language :: Python :: 3
Classifier: Programming Language :: Python :: 3.7
Classifier: Programming Language :: Python :: 3.8
Classifier: Programming Language :: Python :: 3.9
Classifier: Programming Language :: Python :: 3.10
Classifier: Programming Language :: Python :: 3.11
Classifier: Operating System :: OS Independent
Requires-Python: >=3.7
Requires-Dist: google-api-python-client (>=2.0.0)
Requires-Dist: google-auth (>=2.0.0)
